{
  "bill_id": "119-hr-2748",
  "congress": 119,
  "bill_type": "hr",
  "bill_number": "2748",
  "title": "First Time Homeowner Savings Plan Act",
  "short_title": "First Time Homeowner Savings Plan Act",
  "introduced_date": "2025-04-08",
  "update_date": "2025-05-09",
  "stage_label": "Referred to the House Committee on Ways and Means.",
  "text_url": "https://www.congress.gov/119/bills/hr2748/BILLS-119hr2748ih.htm",
  "sponsor_name": "Rep. Stevens, Haley M. [D-MI-11]",
  "sponsor_party": "D",
  "sponsor_state": "MI",
  "policy_area": "Taxation",
  "subjects": [],
  "crs_summary": "",
  "cosponsor_count": 0,
  "current_status": "referred_to_committee",
  "status_date": "2025-04-08",
  "last_action_date": "2025-04-08",
  "last_action_text": "Referred to the House Committee on Ways and Means.",
  "passed_house": false,
  "passed_house_date": "",
  "passed_senate": false,
  "passed_senate_date": "",
  "became_law": false,
  "became_law_date": "",
  "vetoed": false,
  "vetoed_date": "",
  "simplified_complete": true,
  "queued_at": "2026-04-05T02:33:52.339062+00:00",
  "version_hash": "3df0d55ac45051a0",
  "last_processed": "2026-04-05T03:55:48.583973+00:00",
  "section_count": 2
}