{
  "bill_id": "119-hr-107",
  "congress": 119,
  "bill_type": "hr",
  "bill_number": "107",
  "title": "Return to Work Act",
  "short_title": "Return to Work Act",
  "introduced_date": "2025-01-03",
  "update_date": "2025-03-07",
  "stage_label": "Referred to the House Committee on Oversight and Government Reform.",
  "text_url": "https://www.congress.gov/119/bills/hr107/BILLS-119hr107ih.htm",
  "sponsor_name": "Rep. Biggs, Andy [R-AZ-5]",
  "sponsor_party": "R",
  "sponsor_state": "AZ",
  "policy_area": "Government Operations and Politics",
  "subjects": [
    "Commuting",
    "Computers and information technology",
    "Government employee pay, benefits, personnel management"
  ],
  "crs_summary": "Return to Work Act This bill requires the head of each executive agency to reinstate the telework policies in use by that agency on December 31, 2019.",
  "cosponsor_count": 0,
  "current_status": "referred_to_committee",
  "status_date": "2025-01-03",
  "last_action_date": "2025-01-03",
  "last_action_text": "Referred to the House Committee on Oversight and Government Reform.",
  "passed_house": false,
  "passed_house_date": "",
  "passed_senate": false,
  "passed_senate_date": "",
  "became_law": false,
  "became_law_date": "",
  "vetoed": false,
  "vetoed_date": "",
  "simplified_complete": true,
  "queued_at": "2026-03-20T02:37:09.670699+00:00",
  "version_hash": "6e0f94e6209ea0b0",
  "last_processed": "2026-03-20T16:07:44.988337+00:00",
  "section_count": 2
}