{
  "bill_id": "119-hr-302",
  "congress": 119,
  "bill_type": "hr",
  "bill_number": "302",
  "title": "Water Rights Protection Act",
  "short_title": "Water Rights Protection Act",
  "introduced_date": "2025-01-09",
  "update_date": "2025-12-10",
  "stage_label": "Committee on Agriculture discharged.",
  "text_url": "https://www.congress.gov/119/bills/hr302/BILLS-119hr302rh.htm",
  "sponsor_name": "Rep. Maloy, Celeste [R-UT-2]",
  "sponsor_party": "R",
  "sponsor_state": "UT",
  "policy_area": "Public Lands and Natural Resources",
  "subjects": [
    "Administrative law and regulatory procedures",
    "Department of Agriculture",
    "Department of the Interior",
    "Indian lands and resources rights",
    "Intergovernmental relations",
    "Land use and conservation",
    "Licensing and registrations",
    "State and local government operations",
    "Water use and supply"
  ],
  "crs_summary": "Water Rights Protection Act of 2025 This bill limits the transfer of&nbsp;water rights from water users to the Department of the Interior or the Department of Agriculture (USDA). First, the bill&nbsp;prohibits Interior and USDA from conditioning the issuance or renewal of&nbsp;land use or occupancy agreements (e.g., permits and leases) on the transfer of any water right to the United States. Next, it prohibits Interior and USDA from&nbsp;requiring water users, including Indian tribes,&nbsp;to acquire water rights in the name of the United States as a condition of the issuance or renewal of a land use or occupancy agreement. Finally, it prohibits Interior and USDA from&nbsp;conditioning or withholding the issuance or renewal of land use or occupancy agreements on (1) limiting the date, time, quantity, location of diversion or pumping, or place of use of a&nbsp;state water right beyond any applicable limitations under&nbsp;state water law; or (2)&nbsp;modifying&nbsp;the terms and conditions of groundwater withdrawal, guidance and reporting procedures, or conservation and source protection measures established by a state. Interior and&nbsp;USDA must also ensure that federal action imposes no greater restriction or regulatory requirement than under applicable state water law. Further, Interior and USDA must not take actions that adversely affect state authority in permitting water usage or in adjudicating water rights.",
  "cosponsor_count": 6,
  "current_status": "committee_reported",
  "status_date": "2025-11-25",
  "last_action_date": "2025-11-25",
  "last_action_text": "Placed on the Union Calendar, Calendar No. 334.",
  "passed_house": false,
  "passed_house_date": "",
  "passed_senate": false,
  "passed_senate_date": "",
  "became_law": false,
  "became_law_date": "",
  "vetoed": false,
  "vetoed_date": "",
  "simplified_complete": true,
  "queued_at": "2026-03-20T02:54:12.055840+00:00",
  "version_hash": "2eee3beb3a3594e6",
  "last_processed": "2026-03-20T15:48:48.418792+00:00",
  "section_count": 5
}