{
  "bill_id": "119-s-181",
  "congress": 119,
  "bill_type": "s",
  "bill_number": "181",
  "title": "A bill to require agencies submit zero-based budgets.",
  "short_title": "",
  "introduced_date": "2025-01-22",
  "update_date": "2025-02-28",
  "stage_label": "Read twice and referred to the Committee on Homeland Security and Governmental Affairs.",
  "text_url": "https://www.congress.gov/119/bills/s181/BILLS-119s181is.htm",
  "sponsor_name": "Sen. Risch, James E. [R-ID]",
  "sponsor_party": "R",
  "sponsor_state": "ID",
  "policy_area": "Economics and Public Finance",
  "subjects": [
    "Appropriations",
    "Budget deficits and national debt",
    "Budget process",
    "Congressional oversight",
    "Executive agency funding and structure"
  ],
  "crs_summary": "This bill requires federal agencies to submit zero-based budgets to the Office of Management and Budget and the congressional budget committees .&nbsp; Under the bill, a &nbsp;zero-based budget is a systematic budget analysis in which managers (1) examine current objectives, operations, and costs; (2) consider alternative ways of carrying out programs or activities; and (3) rank different programs or activities by order of importance. The bill also requires federal agencies to submit recommendations to reduce spending by at least 2% from the previous year's levels. The Department of Defense and the National Nuclear Security Administration are exempt from this requirement.",
  "cosponsor_count": 6,
  "current_status": "referred_to_committee",
  "status_date": "2025-01-22",
  "last_action_date": "2025-01-22",
  "last_action_text": "Read twice and referred to the Committee on Homeland Security and Governmental Affairs.",
  "passed_house": false,
  "passed_house_date": "",
  "passed_senate": false,
  "passed_senate_date": "",
  "became_law": false,
  "became_law_date": "",
  "vetoed": false,
  "vetoed_date": "",
  "simplified_complete": true,
  "queued_at": "2026-03-20T03:51:38.284208+00:00",
  "version_hash": "b2637c2b9a1ed6a1",
  "last_processed": "2026-03-20T15:58:04.041666+00:00",
  "section_count": 1
}