{
  "bill_id": "119-hr-564",
  "title": "Repeal the TikTok Ban Act",
  "short_title": "Repeal the TikTok Ban Act",
  "congress": 119,
  "bill_number": "HR.564",
  "introduced_date": "2025-01-20",
  "stage": "reported_by_committee",
  "stage_label": "Referred to the House Committee on Energy and Commerce.",
  "version_hash": "69b12efa08851e8c",
  "last_updated": "2026-03-20T16:05:19.737347+00:00",
  "plain_summary": "This bill removes a law that was made to control apps owned by countries that are enemies of the United States. The old law put restrictions on certain apps and websites to keep them from operating in America. This new bill takes away all of those restrictions and lets those apps work freely again. It completely gets rid of the rules that were blocking foreign-owned apps from being used in the United States.",
  "current_status": "referred_to_committee",
  "status_date": "2025-01-20",
  "last_action_date": "2025-01-20",
  "last_action_text": "Referred to the House Committee on Energy and Commerce.",
  "passed_house": false,
  "passed_senate": false,
  "became_law": false,
  "vetoed": false,
  "policy_area": "Science, Technology, Communications",
  "subjects": [],
  "sponsor_name": "Rep. Khanna, Ro [D-CA-17]",
  "sponsor_party": "D",
  "sponsor_state": "CA",
  "cosponsor_count": 1,
  "crs_summary_available": false,
  "plain_keywords": [
    "TikTok ban",
    "foreign apps",
    "Chinese apps",
    "app restrictions",
    "social media ban",
    "enemy countries apps",
    "unblock apps",
    "remove app ban",
    "foreign owned apps",
    "TikTok unban"
  ],
  "sections": [
    {
      "id": "s1",
      "slug": "section-1-short-title",
      "title": "Section 1 Short Title",
      "text": "This law can be called the Repeal the TikTok Ban Act.",
      "word_offset": 0,
      "char_offset": 0
    },
    {
      "id": "s2",
      "slug": "section-2-repeal-of-protecting-americans-from-foreign-adversary-controlled-applications-act",
      "title": "Section 2 Repeal of Protecting Americans from Foreign Adversary Controlled Applications Act",
      "text": "This section cancels an existing law called the Protecting Americans from Foreign Adversary Controlled Applications Act. This existing law was created to control apps that the government believes are controlled by foreign enemies. The section has two main parts. First, the entire existing law is completely removed and no longer has any power. Second, any app or website that was previously labeled as being controlled by a foreign enemy under the old law will no longer have that label. This means those apps and websites can operate normally again, as if they were never restricted.",
      "word_offset": 11,
      "char_offset": 54
    }
  ]
}