{
  "bill_id": "119-s-270",
  "congress": 119,
  "bill_type": "s",
  "bill_number": "270",
  "title": "Natural Disaster Resilience and Recovery Accountability Act",
  "short_title": "Natural Disaster Resilience and Recovery Accountability Act",
  "introduced_date": "2025-01-28",
  "update_date": "2025-04-30",
  "stage_label": "Read twice and referred to the Committee on Homeland Security and Governmental Affairs.",
  "text_url": "https://www.congress.gov/119/bills/s270/BILLS-119s270is.htm",
  "sponsor_name": "Sen. Lankford, James [R-OK]",
  "sponsor_party": "R",
  "sponsor_state": "OK",
  "policy_area": "Emergency Management",
  "subjects": [],
  "crs_summary": "Natural Disaster Resilience and Recovery Accountability Act This bill establishes the Commission on Federal Natural Disaster Resilience and Recovery within the Office of Management and Budget (OMB) to examine and recommend reforms to improve federal programs and activities relating to natural disaster resilience and recovery. OMB must appoint 15 members to serve on the commission. The bill requires federal agencies to advise the commission and furnish information upon request.&nbsp; The commission must hold its first meeting within 240 days after the bill’s enactment. Within two years after its first meeting, the commission must submit a final report to Congress. The report must provide recommendations to improve the federal government’s approach to natural disaster resilience and recovery, including program evaluation and specific policy recommendations. The commission terminates 60 days after it submits the final report.",
  "cosponsor_count": 0,
  "current_status": "referred_to_committee",
  "status_date": "2025-01-28",
  "last_action_date": "2025-01-28",
  "last_action_text": "Read twice and referred to the Committee on Homeland Security and Governmental Affairs.",
  "passed_house": false,
  "passed_house_date": "",
  "passed_senate": false,
  "passed_senate_date": "",
  "became_law": false,
  "became_law_date": "",
  "vetoed": false,
  "vetoed_date": "",
  "simplified_complete": true,
  "queued_at": "2026-04-05T02:16:31.968659+00:00",
  "version_hash": "0f2d10f359f35a71",
  "last_processed": "2026-04-05T04:20:26.988329+00:00",
  "section_count": 2
}