{
  "bill_id": "119-hres-171",
  "title": "Reaffirming the Twenty-second Amendment.",
  "short_title": "",
  "congress": 119,
  "bill_number": "HRES.171",
  "introduced_date": "2025-02-27",
  "stage": "referred_to_committee",
  "stage_label": "In Committee",
  "version_hash": "0c54f28f51dbbddd",
  "last_updated": "2026-04-05T03:04:14.133274+00:00",
  "plain_summary": "This resolution reminds everyone that the Constitution says presidents can only serve two terms total. It points out that President Trump has already served one full term as president. The resolution lists several times when Trump suggested he might try to stay in office longer than the law allows. It makes clear that because of the Twenty-second Amendment to the Constitution, Trump cannot run for president again since he would exceed the two-term limit.",
  "current_status": "referred_to_committee",
  "status_date": "2025-02-27",
  "last_action_date": "2025-02-27",
  "last_action_text": "Referred to the House Committee on the Judiciary.",
  "passed_house": false,
  "passed_senate": false,
  "became_law": false,
  "vetoed": false,
  "policy_area": "Government Operations and Politics",
  "subjects": [],
  "sponsor_name": "Rep. Goldman, Daniel S. [D-NY-10]",
  "sponsor_party": "D",
  "sponsor_state": "NY",
  "cosponsor_count": 28,
  "crs_summary_available": true,
  "plain_keywords": [
    "presidential term limits",
    "two term limit",
    "Trump third term",
    "constitution term limits",
    "president serve twice",
    "22nd amendment",
    "presidential election limits",
    "Trump run again",
    "president term restrictions",
    "constitutional term limits"
  ],
  "sections": [
    {
      "id": "s1",
      "slug": "resolution-reaffirming-the-twenty-second-amendment",
      "title": "Resolution Reaffirming the Twenty-second Amendment",
      "text": "This is a resolution from the House of Representatives that states the Twenty-second Amendment to the Constitution still applies. The Twenty-second Amendment is a rule that says a person can only serve as President of the United States for two terms. The resolution lists many times when President Trump talked about maybe staying in office longer than two terms or serving more than the allowed time. These comments happened between two thousand eighteen and two thousand twenty-five. The resolution ends by saying two things. First, it confirms that the Twenty-second Amendment means a person can only serve two terms total as President. Second, it confirms that this amendment stops President Trump from running for President again because he has already served two terms.",
      "word_offset": 0,
      "char_offset": 0
    }
  ]
}