{
  "bill_id": "119-hr-28",
  "congress": 119,
  "bill_type": "hr",
  "bill_number": "28",
  "title": "Protection of Women and Girls in Sports Act of 2025",
  "short_title": "Protection of Women and Girls in Sports Act of 2025",
  "introduced_date": "2025-01-03",
  "update_date": "2025-07-21",
  "stage_label": "Ms. Adams moved to recommit to the Committee on Education and Workforce. (text: CR H137)",
  "text_url": "https://www.congress.gov/119/bills/hr28/BILLS-119hr28eh.htm",
  "sponsor_name": "Rep. Steube, W. Gregory [R-FL-17]",
  "sponsor_party": "R",
  "sponsor_state": "FL",
  "policy_area": "Civil Rights and Liberties, Minority Issues",
  "subjects": [
    "Athletes",
    "Education programs funding",
    "School athletics",
    "Sex, gender, sexual orientation discrimination"
  ],
  "crs_summary": "Protection of Women and Girls in Sports Act of 2025 This bill generally prohibits school athletic programs from allowing individuals whose biological sex at birth was male to participate in programs that are for women or girls. Specifically, the bill provides that it is a violation of Title IX of the Education Amendments of 1972 for federally funded education programs or activities to operate, sponsor, or facilitate athletic programs or activities that allow individuals of the male sex to participate in programs or activities that are designated for women or girls. (Title IX prohibits discrimination on the basis of sex in federally funded education programs or activities, including in public elementary and secondary schools and in colleges and universities.) Under the bill, sex is based on an individual's reproductive biology and genetics at birth. The bill does not prohibit male individuals from training or practicing with programs or activities for women or girls as long as such training or practice does not deprive any female of corresponding opportunities or benefits. The Government Accountability Office must report on the benefits for women or girls in single-sex sports that would be lost as a result of male participation. In particular, the report must document the negative psychological, developmental, participatory, and sociological effects of male participation on girls.",
  "cosponsor_count": 83,
  "current_status": "referred_to_committee",
  "status_date": "2025-01-03",
  "last_action_date": "2025-01-15",
  "last_action_text": "Received in the Senate.",
  "passed_house": false,
  "passed_house_date": "",
  "passed_senate": false,
  "passed_senate_date": "",
  "became_law": false,
  "became_law_date": "",
  "vetoed": false,
  "vetoed_date": "",
  "simplified_complete": true,
  "queued_at": "2026-03-20T02:29:05.931403+00:00",
  "version_hash": "e0c24e442328b635",
  "last_processed": "2026-03-20T14:06:19.729718+00:00",
  "section_count": 2
}