{
  "bill_id": "119-hres-37",
  "congress": 119,
  "bill_type": "hres",
  "bill_number": "37",
  "title": "Recognizing the 4th anniversary of the Trump administration's Secretary of the Air Force announcing Redstone Arsenal in Huntsville, Alabama, as the preferred location for United States Space Command Headquarters.",
  "short_title": "",
  "introduced_date": "2025-01-13",
  "update_date": "2025-12-05",
  "stage_label": "Referred to the House Committee on Armed Services.",
  "text_url": "https://www.congress.gov/119/bills/hres37/BILLS-119hres37ih.htm",
  "sponsor_name": "Rep. Strong, Dale W. [R-AL-5]",
  "sponsor_party": "R",
  "sponsor_state": "AL",
  "policy_area": "Armed Forces and National Security",
  "subjects": [
    "Alabama",
    "Commemorative events and holidays",
    "Military facilities and property"
  ],
  "crs_summary": "This resolution expresses recognition that the Air Force’s Strategic Basing Action process complied with law and policy and was justified in identifying Huntsville, Alabama, as the preferred permanent location for Space Command Headquarters.",
  "cosponsor_count": 3,
  "current_status": "referred_to_committee",
  "status_date": "2025-01-13",
  "last_action_date": "2025-01-13",
  "last_action_text": "Referred to the House Committee on Armed Services.",
  "passed_house": false,
  "passed_house_date": "",
  "passed_senate": false,
  "passed_senate_date": "",
  "became_law": false,
  "became_law_date": "",
  "vetoed": false,
  "vetoed_date": "",
  "simplified_complete": true,
  "queued_at": "2026-03-20T03:07:45.038735+00:00",
  "version_hash": "ab46d39eeaa5b20f",
  "last_processed": "2026-03-20T12:16:39.679395+00:00",
  "section_count": 5
}