{
  "bill_id": "119-s-99",
  "congress": 119,
  "bill_type": "s",
  "bill_number": "99",
  "title": "Strengthening Support for American Manufacturing Act",
  "short_title": "Strengthening Support for American Manufacturing Act",
  "introduced_date": "2025-01-15",
  "update_date": "2025-12-01",
  "stage_label": "Committee on Commerce, Science, and Transportation. Reported by Senator Cruz without amendment. With written report No. ",
  "text_url": "https://www.congress.gov/119/bills/s99/BILLS-119s99es.htm",
  "sponsor_name": "Sen. Peters, Gary C. [D-MI]",
  "sponsor_party": "D",
  "sponsor_state": "MI",
  "policy_area": "Commerce",
  "subjects": [
    "Advanced technology and technological innovations",
    "Advisory bodies",
    "Congressional oversight",
    "Industrial policy and productivity",
    "Manufacturing",
    "Product development and innovation"
  ],
  "crs_summary": "Strengthening Support for American Manufacturing Act This bill requires the Department of Commerce to contract with the National Academy of Public Administration to study and report on the offices and bureaus of the department that are relevant to critical supply chain resilience and manufacturing and industrial innovation. The report must evaluate the purpose, statutory authority, effectiveness, efficiency, and limitations of each such office and bureau and provide recommendations to improve their effectiveness, efficiency, and impact.",
  "cosponsor_count": 1,
  "current_status": "passed_senate",
  "status_date": "2025-10-23",
  "last_action_date": "2025-10-24",
  "last_action_text": "Held at the desk.",
  "passed_house": false,
  "passed_house_date": "",
  "passed_senate": true,
  "passed_senate_date": "2025-10-23",
  "became_law": false,
  "became_law_date": "",
  "vetoed": false,
  "vetoed_date": "",
  "simplified_complete": true,
  "queued_at": "2026-03-20T03:24:50.902946+00:00",
  "version_hash": "babd8ee2b55e6b6e",
  "last_processed": "2026-03-20T12:45:36.326718+00:00",
  "section_count": 3
}