{
  "bill_id": "119-hr-171",
  "title": "Make Transportation Authorities Accountable and Transparent Act",
  "short_title": "Make Transportation Authorities Accountable and Transparent Act",
  "congress": 119,
  "bill_number": "HR.171",
  "introduced_date": "2025-01-03",
  "stage": "reported_by_committee",
  "stage_label": "Referred to the Subcommittee on Highways and Transit.",
  "version_hash": "166a4ce98f0dce18",
  "last_updated": "2026-03-20T13:45:45.163500+00:00",
  "plain_summary": "This bill tells a government watchdog office to check how the five biggest public transportation systems in the country spent their federal money over the last five years. The watchdog must look at all the money these transit agencies got from the government, including special coronavirus relief money. After they finish checking the spending, the watchdog office must write a report about what they found and give it to Congress within six months.",
  "current_status": "referred_to_committee",
  "status_date": "2025-01-04",
  "last_action_date": "2025-01-04",
  "last_action_text": "Referred to the Subcommittee on Highways and Transit.",
  "passed_house": false,
  "passed_senate": false,
  "became_law": false,
  "vetoed": false,
  "policy_area": "Government Operations and Politics",
  "subjects": [
    "Accounting and auditing",
    "Congressional oversight",
    "Government studies and investigations",
    "Public transit",
    "Transportation programs funding"
  ],
  "sponsor_name": "Rep. Malliotakis, Nicole [R-NY-11]",
  "sponsor_party": "R",
  "sponsor_state": "NY",
  "cosponsor_count": 1,
  "crs_summary_available": true,
  "plain_keywords": [
    "public transportation audit",
    "transit agency spending",
    "subway bus money check",
    "government watchdog investigation",
    "federal transportation funding",
    "coronavirus transit relief",
    "public transit accountability",
    "transportation authority oversight",
    "metro system spending review",
    "government audit public transport"
  ],
  "sections": [
    {
      "id": "s1",
      "slug": "section-1-short-title",
      "title": "Section 1  Short Title",
      "text": "This law can be called the Make Transportation Authorities Accountable and Transparent Act.",
      "word_offset": 0,
      "char_offset": 0
    },
    {
      "id": "s2",
      "slug": "section-2-inspector-general-audit",
      "title": "Section 2  Inspector General Audit on Public Transportation Coronavirus Relief Spending",
      "text": "The inspector general (a government watchdog who checks how money is spent) of the Department of Transportation must check how certain public transportation agencies used federal money during the five years before this law was passed. The inspector general must look at the five biggest public transportation agencies in the country. These are the agencies that had the most individual passenger trips in two thousand nineteen. The audit (detailed money check) must show how much money each agency got from federal coronavirus relief laws and regular transportation funding. It must also explain exactly how they spent that money. The inspector general has one hundred eighty days after this law passes to finish the audit and send a report to Congress. The laws being checked include regular transportation funding laws and several coronavirus relief laws passed in two thousand twenty and two thousand twenty-one. These include the Coronavirus Preparedness and Response Supplemental Appropriations Act from two thousand twenty, the Coronavirus Aid Relief and Economic Security Act, the Consolidated Appropriations Act from two thousand twenty-one, and the American Rescue Plan Act from two thousand twenty-one.",
      "word_offset": 13,
      "char_offset": 92
    }
  ]
}