{
  "bill_id": "119-hr-211",
  "congress": 119,
  "bill_type": "hr",
  "bill_number": "211",
  "title": "Equal Access to Contraception for Veterans Act",
  "short_title": "Equal Access to Contraception for Veterans Act",
  "introduced_date": "2025-01-06",
  "update_date": "2025-12-10",
  "stage_label": "Referred to the Subcommittee on Health.",
  "text_url": "https://www.congress.gov/119/bills/hr211/BILLS-119hr211ih.htm",
  "sponsor_name": "Rep. Brownley, Julia [D-CA-26]",
  "sponsor_party": "D",
  "sponsor_state": "CA",
  "policy_area": "Armed Forces and National Security",
  "subjects": [
    "Family planning and birth control",
    "Health care costs and insurance",
    "Health care coverage and access",
    "Veterans' medical care",
    "Women's health"
  ],
  "crs_summary": "Equal Access to Contraception for Veterans Act This bill prohibits the Department of Veterans Affairs from requiring payment from a veteran for any contraceptive item that is required to be covered by health insurance plans without a cost-sharing requirement.",
  "cosponsor_count": 84,
  "current_status": "referred_to_committee",
  "status_date": "2025-02-06",
  "last_action_date": "2025-02-06",
  "last_action_text": "Referred to the Subcommittee on Health.",
  "passed_house": false,
  "passed_house_date": "",
  "passed_senate": false,
  "passed_senate_date": "",
  "became_law": false,
  "became_law_date": "",
  "vetoed": false,
  "vetoed_date": "",
  "simplified_complete": true,
  "queued_at": "2026-03-20T02:47:57.200357+00:00",
  "version_hash": "88f8b9898c105e72",
  "last_processed": "2026-03-20T12:33:32.342195+00:00",
  "section_count": 2
}